blab/1.txt
blab/__init__.py
blab/__main__.py
blab/blab_startup.ipynb
blab/blab_tools.py
blab-0.2.2.dist-info/licenses/LICENSE
blab-0.2.2.dist-info/METADATA
blab-0.2.2.dist-info/WHEEL
blab-0.2.2.dist-info/entry_points.txt
blab-0.2.2.dist-info/top_level.txt
blab-0.2.2.dist-info/RECORD
