Metadata-Version: 2.4
Name: blab
Version: 0.2.2
Summary: Various Jupyter Tools
Author-email: djekra <hopsalla@gmail.com>
License-Expression: MIT
Project-URL: Homepage, https://github.com/djekra/blab
Requires-Python: >=3.10
License-File: LICENSE
Requires-Dist: bpyth>=0.2.1
Requires-Dist: importlib_resources
Requires-Dist: nbformat
Requires-Dist: nbconvert
Requires-Dist: ipytest
Requires-Dist: matplotlib
Provides-Extra: dev
Requires-Dist: jupyterlab>=4.3.6; extra == "dev"
Dynamic: license-file
